py_aioclient/__init__.py
py_aioclient/api.py
py_aioclient/client.py
py_aioclient-0.1.7.dist-info/LICENCE
py_aioclient-0.1.7.dist-info/METADATA
py_aioclient-0.1.7.dist-info/WHEEL
py_aioclient-0.1.7.dist-info/RECORD
