Metadata-Version: 2.1
Name: py-aioclient
Version: 0.1.7
Summary: Um cliente HTTP assíncrono e leve para Python, com uma API simplificada para requisições fáceis e concorrentes.
License: MIT
Author: Abel Salim
Author-email: abelsalim@proton.me
Requires-Python: >=3.10,<4.0
Classifier: License :: OSI Approved :: MIT License
Classifier: Programming Language :: Python :: 3
Classifier: Programming Language :: Python :: 3.10
Classifier: Programming Language :: Python :: 3.11
Classifier: Programming Language :: Python :: 3.12
Classifier: Programming Language :: Python :: 3.13
Requires-Dist: aiohttp (>=3.12.13,<4.0.0)
